ol_openedx_course_structure_api/__init__.py
ol_openedx_course_structure_api/app.py
ol_openedx_course_structure_api/urls.py
ol_openedx_course_structure_api/views.py
ol_openedx_course_structure_api/settings/__init__.py
ol_openedx_course_structure_api/settings/common.py
ol_openedx_course_structure_api/settings/production.py
ol_openedx_course_structure_api-0.2.0.dist-info/METADATA
ol_openedx_course_structure_api-0.2.0.dist-info/WHEEL
ol_openedx_course_structure_api-0.2.0.dist-info/entry_points.txt
ol_openedx_course_structure_api-0.2.0.dist-info/licenses/LICENSE.txt
ol_openedx_course_structure_api-0.2.0.dist-info/RECORD
